odoo/addons/pos_sale_order_print/README.rst
odoo/addons/pos_sale_order_print/__init__.py
odoo/addons/pos_sale_order_print/__manifest__.py
odoo/addons/pos_sale_order_print/i18n/es.po
odoo/addons/pos_sale_order_print/i18n/it.po
odoo/addons/pos_sale_order_print/i18n/pos_sale_order_print.pot
odoo/addons/pos_sale_order_print/models/__init__.py
odoo/addons/pos_sale_order_print/models/pos_config.py
odoo/addons/pos_sale_order_print/models/pos_session.py
odoo/addons/pos_sale_order_print/models/res_config_settings.py
odoo/addons/pos_sale_order_print/readme/CONFIGURE.rst
odoo/addons/pos_sale_order_print/readme/CONTRIBUTORS.rst
odoo/addons/pos_sale_order_print/readme/DESCRIPTION.rst
odoo/addons/pos_sale_order_print/readme/USAGE.rst
odoo/addons/pos_sale_order_print/static/description/banner.png
odoo/addons/pos_sale_order_print/static/description/icon.png
odoo/addons/pos_sale_order_print/static/description/icon.svg
odoo/addons/pos_sale_order_print/static/description/index.html
odoo/addons/pos_sale_order_print/static/img/pos_config.png
odoo/addons/pos_sale_order_print/static/img/pos_print_popup.png
odoo/addons/pos_sale_order_print/static/img/pos_sale_order.png
odoo/addons/pos_sale_order_print/static/img/pos_standard_popup.png
odoo/addons/pos_sale_order_print/static/src/js/SaleOrderManagementScreen.esm.js
odoo/addons/pos_sale_order_print/static/src/js/pos_sale_order_print.esm.js
odoo/addons/pos_sale_order_print/views/res_config_settings_view.xml
odoo_addon_pos_sale_order_print-16.0.1.0.2.dist-info/METADATA
odoo_addon_pos_sale_order_print-16.0.1.0.2.dist-info/WHEEL
odoo_addon_pos_sale_order_print-16.0.1.0.2.dist-info/top_level.txt
odoo_addon_pos_sale_order_print-16.0.1.0.2.dist-info/RECORD
